[
    {
        "domain": ".instagram.com",
        "expirationDate": 1813211786.960785,
        "hostOnly": false,
        "httpOnly": false,
        "name": "csrftoken",
        "path": "/",
        "sameSite": "unspecified",
        "secure": true,
        "session": false,
        "storeId": "0",
        "value": "JgYdciajUac5INIKEvmliCDwv5eu76EJ",
        "id": 1
    },
    {
        "domain": ".instagram.com",
        "expirationDate": 1805269627.236064,
        "hostOnly": false,
        "httpOnly": true,
        "name": "datr",
        "path": "/",
        "sameSite": "no_restriction",
        "secure": true,
        "session": false,
        "storeId": "0",
        "value": "euKKaZH0bl4nxzb-oNvkJPLn",
        "id": 2
    },
    {
        "domain": ".instagram.com",
        "expirationDate": 1779256569,
        "hostOnly": false,
        "httpOnly": false,
        "name": "dpr",
        "path": "/",
        "sameSite": "no_restriction",
        "secure": true,
        "session": false,
        "storeId": "0",
        "value": "1.25",
        "id": 3
    },
    {
        "domain": ".instagram.com",
        "expirationDate": 1786427786.961149,
        "hostOnly": false,
        "httpOnly": false,
        "name": "ds_user_id",
        "path": "/",
        "sameSite": "no_restriction",
        "secure": true,
        "session": false,
        "storeId": "0",
        "value": "59530233345",
        "id": 4
    },
    {
        "domain": ".instagram.com",
        "expirationDate": 1802243535.921862,
        "hostOnly": false,
        "httpOnly": true,
        "name": "ig_did",
        "path": "/",
        "sameSite": "unspecified",
        "secure": true,
        "session": false,
        "storeId": "0",
        "value": "C6669396-4FE8-4361-9C1C-52DF7DAD25BF",
        "id": 5
    },
    {
        "domain": ".instagram.com",
        "expirationDate": 1785746938.041462,
        "hostOnly": false,
        "httpOnly": true,
        "name": "mid",
        "path": "/",
        "sameSite": "no_restriction",
        "secure": true,
        "session": false,
        "storeId": "0",
        "value": "aGD9-QALAAEmijUpk5bENEou_L95",
        "id": 6
    },
    {
        "domain": ".instagram.com",
        "expirationDate": 1805272059.798692,
        "hostOnly": false,
        "httpOnly": true,
        "name": "ps_l",
        "path": "/",
        "sameSite": "lax",
        "secure": true,
        "session": false,
        "storeId": "0",
        "value": "1",
        "id": 7
    },
    {
        "domain": ".instagram.com",
        "expirationDate": 1805272059.799111,
        "hostOnly": false,
        "httpOnly": true,
        "name": "ps_n",
        "path": "/",
        "sameSite": "no_restriction",
        "secure": true,
        "session": false,
        "storeId": "0",
        "value": "1",
        "id": 8
    },
    {
        "domain": ".instagram.com",
        "hostOnly": false,
        "httpOnly": true,
        "name": "rur",
        "path": "/",
        "sameSite": "lax",
        "secure": true,
        "session": true,
        "storeId": "0",
        "value": "\"EAG\\05459530233345\\0541810187787:01febb2e996a3db8470618cd02155d4809c7b8f14c8afc2c8f25dd87078319d52ab4bc7f\"",
        "id": 9
    },
    {
        "domain": ".instagram.com",
        "expirationDate": 1810187786.961355,
        "hostOnly": false,
        "httpOnly": true,
        "name": "sessionid",
        "path": "/",
        "sameSite": "unspecified",
        "secure": true,
        "session": false,
        "storeId": "0",
        "value": "59530233345%3Ao18TtxurvD4LIQ%3A25%3AAYjTTsB75Hpk9wvXnWT4EQwg_yHHUeD2_I64Ccoh76w",
        "id": 10
    },
    {
        "domain": ".instagram.com",
        "expirationDate": 1779256569,
        "hostOnly": false,
        "httpOnly": false,
        "name": "wd",
        "path": "/",
        "sameSite": "lax",
        "secure": true,
        "session": false,
        "storeId": "0",
        "value": "1536x730",
        "id": 11
    }
]